django_simple_grpc/__init__.py
django_simple_grpc/client.py
django_simple_grpc/server.py
django_simple_grpc/management/__init__.py
django_simple_grpc/management/commands/__init__.py
django_simple_grpc/management/commands/grpc_auto_proto.py
django_simple_grpc/management/commands/grpc_create_service.py
django_simple_grpc/management/commands/grpc_generate.py
django_simple_grpc/management/commands/run_grpc.py
django_simple_grpc-0.1.1.dist-info/licenses/LICENSE
django_simple_grpc-0.1.1.dist-info/METADATA
django_simple_grpc-0.1.1.dist-info/WHEEL
django_simple_grpc-0.1.1.dist-info/top_level.txt
django_simple_grpc-0.1.1.dist-info/RECORD
