Metadata-Version: 2.4
Name: django-simple-grpc
Version: 0.1.1
Summary: Simplify gRPC server and client usage in Django apps.
Home-page: https://github.com/HosseinFattahi/django-simple-grpc
Author: HF
Author-email: hofattahi98@gmail.com
Project-URL: Bug Tracker, https://github.com/HosseinFattahi/django-simple-grpc/issues
Project-URL: Source, https://github.com/HosseinFattahi/django-simple-grpc
Keywords: django grpc grpcio microservices python server client
Classifier: Development Status :: 4 - Beta
Classifier: Intended Audience :: Developers
Classifier: Topic :: Internet :: WWW/HTTP
Classifier: Framework :: Django
Classifier: License :: OSI Approved :: MIT License
Classifier: Programming Language :: Python :: 3
Classifier: Programming Language :: Python :: 3.8
Classifier: Programming Language :: Python :: 3.9
Classifier: Programming Language :: Python :: 3.10
Classifier: Programming Language :: Python :: 3.11
Classifier: Programming Language :: Python :: 3.12
Classifier: Operating System :: OS Independent
Requires-Python: >=3.8
License-File: LICENSE
Requires-Dist: Django>=3.2
Requires-Dist: grpcio==1.71.0
Requires-Dist: grpcio-tools==1.71.0
Requires-Dist: protobuf==5.29.4
Dynamic: author
Dynamic: author-email
Dynamic: classifier
Dynamic: description
Dynamic: description-content-type
Dynamic: home-page
Dynamic: keywords
Dynamic: license-file
Dynamic: project-url
Dynamic: requires-dist
Dynamic: requires-python
Dynamic: summary
